MANIFEST.in
README.rst
README.txt
requirements.txt
setup.cfg
setup.py
FMLocker/__init__.py
FMLocker/const.py
FMLocker/locker.py
FMLocker.egg-info/PKG-INFO
FMLocker.egg-info/SOURCES.txt
FMLocker.egg-info/dependency_links.txt
FMLocker.egg-info/requires.txt
FMLocker.egg-info/top_level.txt